operate/__init__.py
operate/account/__init__.py
operate/account/user.py
operate/bridge/bridge_manager.py
operate/bridge/providers/lifi_provider.py
operate/bridge/providers/native_bridge_provider.py
operate/bridge/providers/provider.py
operate/bridge/providers/relay_provider.py
operate/cli.py
operate/constants.py
operate/data/README.md
operate/data/__init__.py
operate/data/contracts/__init__.py
operate/data/contracts/dual_staking_token/__init__.py
operate/data/contracts/dual_staking_token/build/DualStakingToken.json
operate/data/contracts/dual_staking_token/contract.py
operate/data/contracts/dual_staking_token/contract.yaml
operate/data/contracts/foreign_omnibridge/__init__.py
operate/data/contracts/foreign_omnibridge/build/ForeignOmnibridge.json
operate/data/contracts/foreign_omnibridge/contract.py
operate/data/contracts/foreign_omnibridge/contract.yaml
operate/data/contracts/home_omnibridge/__init__.py
operate/data/contracts/home_omnibridge/build/HomeOmnibridge.json
operate/data/contracts/home_omnibridge/contract.py
operate/data/contracts/home_omnibridge/contract.yaml
operate/data/contracts/l1_standard_bridge/__init__.py
operate/data/contracts/l1_standard_bridge/build/L1StandardBridge.json
operate/data/contracts/l1_standard_bridge/contract.py
operate/data/contracts/l1_standard_bridge/contract.yaml
operate/data/contracts/l2_standard_bridge/__init__.py
operate/data/contracts/l2_standard_bridge/build/L2StandardBridge.json
operate/data/contracts/l2_standard_bridge/contract.py
operate/data/contracts/l2_standard_bridge/contract.yaml
operate/data/contracts/mech_activity/__init__.py
operate/data/contracts/mech_activity/build/MechActivity.json
operate/data/contracts/mech_activity/contract.py
operate/data/contracts/mech_activity/contract.yaml
operate/data/contracts/optimism_mintable_erc20/__init__.py
operate/data/contracts/optimism_mintable_erc20/build/OptimismMintableERC20.json
operate/data/contracts/optimism_mintable_erc20/contract.py
olas_operate_middleware-0.14.5.dist-info/METADATA
olas_operate_middleware-0.14.5.dist-info/WHEEL
olas_operate_middleware-0.14.5.dist-info/entry_points.txt
olas_operate_middleware-0.14.5.dist-info/licenses/LICENSE
olas_operate_middleware-0.14.5.dist-info/RECORD
